snakespawn/__init__.py
snakespawn/licenses.py
snakespawn/main.py
snakespawn-1.1.10.dist-info/LICENSE
snakespawn-1.1.10.dist-info/METADATA
snakespawn-1.1.10.dist-info/WHEEL
snakespawn-1.1.10.dist-info/entry_points.txt
snakespawn-1.1.10.dist-info/top_level.txt
snakespawn-1.1.10.dist-info/RECORD
