Metadata-Version: 2.1
Name: snakespawn
Version: 1.1.10
Summary: A tool for initializing python packages.
Author: William L.
License: MIT
Requires-Python: >=3.10
License-File: LICENSE
Requires-Dist: cli-veripy
